ENPROG/__init__.py
ENPROG/__main__.py
ENPROG/enprog.py
ENPROG/example.py
enprog-0.0.2.dist-info/METADATA
enprog-0.0.2.dist-info/WHEEL
enprog-0.0.2.dist-info/entry_points.txt
enprog-0.0.2.dist-info/top_level.txt
enprog-0.0.2.dist-info/RECORD
